pygtail/__init__.py
pygtail/core.py
pygtail-0.13.0.dist-info/LICENSE
pygtail-0.13.0.dist-info/METADATA
pygtail-0.13.0.dist-info/WHEEL
pygtail-0.13.0.dist-info/entry_points.txt
pygtail-0.13.0.dist-info/top_level.txt
pygtail-0.13.0.dist-info/RECORD
