Metadata-Version: 2.1
Name: pygtail
Version: 0.13.0
Summary: Reads log file lines that have not been read.
Home-page: http://github.com/bgreenlee/pygtail
Author: Brad Greenlee
Author-email: brad@footle.org
License: GPL v2
Keywords: logging,tail,logtail2
Classifier: Development Status :: 4 - Beta
Classifier: Intended Audience :: Developers
Classifier: License :: OSI Approved :: GNU General Public License (GPL)
Classifier: Operating System :: MacOS :: MacOS X
Classifier: Operating System :: POSIX :: Linux
Classifier: Operating System :: Unix
Classifier: Programming Language :: Python
Classifier: Programming Language :: Python :: 2.6
Classifier: Programming Language :: Python :: 2.7
Classifier: Programming Language :: Python :: 3
Classifier: Topic :: Software Development :: Libraries :: Python Modules
Classifier: Topic :: System :: Logging
License-File: LICENSE
